dynamic_forms/__init__.py
dynamic_forms/apps.py
dynamic_forms/boundfields.py
dynamic_forms/formfields.py
dynamic_forms/forms.py
dynamic_forms/models.py
dynamic_forms/utils.py
dynamic_forms/views.py
dynamic_forms/widgets.py
dynamic_forms/templates/dynamic_forms/widgets/formbuilder.html
dynamic_forms/templates/dynamic_forms/widgets/formrender.html
dynamic_forms/templates/dynamic_forms/widgets/subfield.html
dynamic_forms/templates/dynamic_forms/widgets/subfield_crispy.html
dynamic_django_forms-0.1.11.dist-info/LICENSE.txt
dynamic_django_forms-0.1.11.dist-info/METADATA
dynamic_django_forms-0.1.11.dist-info/WHEEL
dynamic_django_forms-0.1.11.dist-info/top_level.txt
dynamic_django_forms-0.1.11.dist-info/RECORD
