Metadata-Version: 2.1
Name: dynamic-django-forms
Version: 0.1.11
Summary: JSON-Powered Dynamic Forms for Django
Home-page: https://github.com/askvortsov1/dynamic-django-forms
Author: Alexander Skvortsov
Author-email: sasha.skvortsov109@gmail.com
Maintainer: Alexander Skvortsov
License: MIT License
Keywords: django,dynamic,forms,json
Platform: UNKNOWN
Classifier: Programming Language :: Python :: 3
Classifier: License :: OSI Approved :: MIT License
Classifier: Operating System :: OS Independent
